<?xml version="1.0" encoding="UTF-8"?>
<gresources>
  <gresource prefix="/io/github/nokse22/Exhibit">
    <file>configurations.json</file>
    <file>style.css</file>
    <file preprocess="xml-stripblanks">ui/window.ui</file>
    <file preprocess="xml-stripblanks">ui/file_row.ui</file>
    <file preprocess="xml-stripblanks">ui/f3d_viewer.ui</file>
    <file preprocess="xml-stripblanks">gtk/help-overlay.ui</file>
    <file preprocess="xml-stripblanks">icons/16x16/actions/go-home-symbolic.svg</file>
    <file preprocess="xml-stripblanks">icons/16x16/actions/orthographic-symbolic.svg</file>
    <file preprocess="xml-stripblanks">icons/16x16/actions/perspective-symbolic.svg</file>
    <file preprocess="xml-stripblanks">icons/16x16/actions/photo-camera-symbolic.svg</file>
    <file preprocess="xml-stripblanks">icons/16x16/actions/image-alt-symbolic.svg</file>
    <file preprocess="xml-stripblanks">icons/16x16/actions/globe-symbolic.svg</file>
    <file preprocess="xml-stripblanks">icons/16x16/actions/left-large-symbolic.svg</file>
    <file preprocess="xml-stripblanks">icons/16x16/actions/arrow-into-box-symbolic.svg</file>
    <file preprocess="xml-stripblanks">icons/16x16/actions/share-symbolic.svg</file>
  </gresource>
</gresources>
